dio62.py
dio62-0.0.2.dist-info/METADATA
dio62-0.0.2.dist-info/WHEEL
dio62-0.0.2.dist-info/license.txt
dio62-0.0.2.dist-info/top_level.txt
dio62-0.0.2.dist-info/RECORD
