Metadata-Version: 2.2
Name: dio62
Version: 0.0.2
Summary: Package to scrape Minecraft recipe to pandas dataframe
Author-email: Hyishiro Honda <honda@gmail.com>
License: Copyright (c) 2025 aknek
Classifier: Programming Language :: Python :: 3
Classifier: Operating System :: OS Independent
Requires-Python: >=3.10
License-File: license.txt
Requires-Dist: requests>=2.32.3
Requires-Dist: beautifulsoup4>=4.13.3
Requires-Dist: pandas>=2.2.3
